{"nodes": [{"id": "menubarapp_appicon", "label": "App Icon (Keycap XE)", "file_type": "image", "source_file": "macos/MenuBarApp/AppIcon.jpg", "source_location": null, "source_url": null, "captured_at": null, "author": null, "contributor": null}], "edges": [{"source": "menubarapp_appicon", "target": "readme_menu_bar_app", "relation": "conceptually_related_to", "confidence": "INFERRED", "confidence_score": 0.85, "source_file": "macos/MenuBarApp/AppIcon.jpg", "source_location": null, "weight": 1.0}, {"source": "menubarapp_appicon", "target": "readme_layout_provider", "relation": "conceptually_related_to", "confidence": "INFERRED", "confidence_score": 0.65, "source_file": "macos/MenuBarApp/AppIcon.jpg", "source_location": null, "weight": 1.0}], "hyperedges": []}